README
arprequest.py
setup.py
arprequest.egg-info/PKG-INFO
arprequest.egg-info/SOURCES.txt
arprequest.egg-info/dependency_links.txt
arprequest.egg-info/top_level.txt