Metadata-Version: 1.0
Name: arprequest
Version: 0.3
Summary: A class which sends an ARP Request to know if a host is online on local networks
Home-page: http://idevelop.org/p/labo/page/ArpRequest/
Author: Antoine Millet
Author-email: antoine@inaps.org
License: WTFPL
Keywords: arp network ethernet
Platform: UNKNOWN
Classifier: Topic :: Communications
Classifier: Topic :: System :: Networking
Classifier: Topic :: System :: Networking :: Monitoring
Classifier: Development Status :: 3 - Alpha
Classifier: Intended Audience :: Developers
Classifier: Intended Audience :: System Administrators
Classifier: License :: Public Domain
Classifier: Operating System :: Unix
Classifier: Programming Language :: Python
